handadoc_client.py
handadoc_client-0.0.1a0.dev7.dist-info/METADATA
handadoc_client-0.0.1a0.dev7.dist-info/WHEEL
handadoc_client-0.0.1a0.dev7.dist-info/entry_points.txt
handadoc_client-0.0.1a0.dev7.dist-info/top_level.txt
handadoc_client-0.0.1a0.dev7.dist-info/RECORD
