Metadata-Version: 2.1
Name: handadoc-client
Version: 0.0.1a0.dev7
Summary: Client for handadoc to hand over documentations to the webserver.
Home-page: https://gitlab.com/david.scheliga/handadoc_client
Author: David Scheliga
License: GNU General Public License V3 (GPLv3)
Project-URL: Documentation, https://handadoc_client.readthedocs.io/en/latest/
Project-URL: Source Code Repository, https://gitlab.com/david.scheliga/handadoc_client
Platform: UNKNOWN
Classifier: Development Status :: 3 - Alpha
Classifier: License :: OSI Approved :: GNU General Public License v3 (GPLv3)
Classifier: Operating System :: OS Independent
Classifier: Programming Language :: Python :: 3
Classifier: Programming Language :: Python :: 3.6
Classifier: Programming Language :: Python :: 3.7
Classifier: Programming Language :: Python :: 3.8
Classifier: Programming Language :: Python :: 3.9
Requires-Dist: click
Requires-Dist: requests
Requires-Dist: jsonschema
Requires-Dist: myminions
